Metadata-Version: 2.1
Name: matmul
Version: 0.0.2
Summary: Matrix Multiplication for 2 matrices
Author: Dhruv Gupta
License: MIT
